pyalgo/__init__.py
pyalgo/algocryption/__init__.py
pyalgo/algocryption/algocryption.py
pyalgo/algocryption/compiled_functions/__init__.py
pyalgo/algocryption/compiled_functions/compiled_functions.py
pyalgo/algocryption/functions_for_in_time_compile/__init__.py
pyalgo/algocryption/functions_for_in_time_compile/functions_for_in_time_compile.py
pyalgo/basic_modules/__init__.py
pyalgo/basic_modules/default_functions.py
pyalgo/basic_modules/default_values.py
pyalgo/basic_modules/algocryption_default_values/__init__.py
pyalgo/basic_modules/algocryption_default_values/Simple_Columnar_Transposition_default_values/Simple_Columnar_Transposition_default_values.py
pyalgo/basic_modules/algocryption_default_values/Simple_Columnar_Transposition_default_values/__init__.py
pyalgo/basic_modules/pytrainer_default_values/__init__.py
pyalgo/basic_modules/pytrainer_default_values/ML_functions_default_values/ML_functions_default_values.py
pyalgo/basic_modules/pytrainer_default_values/ML_functions_default_values/__init__.py
pyalgo/basic_modules/pytrainer_default_values/ML_functions_default_values/ML_functions_trainer_default_values/ML_functions_trainer_default_values.py
pyalgo/basic_modules/pytrainer_default_values/ML_functions_default_values/ML_functions_trainer_default_values/__init__.py
pyalgo/basic_modules/sortalgo_default_values/__init__.py
pyalgo/basic_modules/sortalgo_default_values/sortalgo_default_values.py
pyalgo/basic_modules/sortalgo_default_values/quick_sort_default_values/__init__.py
pyalgo/basic_modules/sortalgo_default_values/quick_sort_default_values/quick_sort_default_values.py
pyalgo/pytrainer/ML_functions.py
pyalgo/pytrainer/__init__.py
pyalgo/pytrainer/pytrainer.py
pyalgo/sortalgo/__init__.py
pyalgo/sortalgo/sortalgo.py
tests/__init__.py
tests/test_functions.py
pyalgo_pkg-0.0.8.dist-info/LICENSE
pyalgo_pkg-0.0.8.dist-info/METADATA
pyalgo_pkg-0.0.8.dist-info/WHEEL
pyalgo_pkg-0.0.8.dist-info/top_level.txt
pyalgo_pkg-0.0.8.dist-info/RECORD
