Metadata-Version: 2.1
Name: pyalgo-pkg
Version: 0.0.8
Summary: A package for basic algorithms
Home-page: UNKNOWN
Author: Gilad Dotan
Author-email: gilad.dotann@egmail.com
License: UNKNOWN
Platform: UNKNOWN
Classifier: Programming Language :: Python :: 3
Classifier: License :: OSI Approved :: MIT License
Classifier: Operating System :: OS Independent
Requires-Python: >=3.8.6
